hiraid/__init__.py
hiraid/cmcustomviews.py
hiraid/cmdview.py
hiraid/cmrest.py
hiraid/cmrestparser.py
hiraid/cmrestswagger.py
hiraid/cmviews.py
hiraid/customhostviews.py
hiraid/customviews.py
hiraid/gadedgemigration.py
hiraid/gadmigration.py
hiraid/hiraidexception.py
hiraid/horcm_instance_manager.py
hiraid/horcm_template.py
hiraid/hostlib.py
hiraid/hostviews.py
hiraid/hvexception.py
hiraid/hvutil.py
hiraid/ldev.py
hiraid/messaging.py
hiraid/raidadmin.py
hiraid/raidcom.py
hiraid/raidcomparser.py
hiraid/raidcomstats.py
hiraid/raidlib.py
hiraid/raidlibStart.py
hiraid/raidlibput.py
hiraid/redhatmultipathdparser.py
hiraid/scriptconf.py
hiraid/sshhost.py
hiraid/storage_utils.py
hiraid/storagecapabilities.py
hiraid/storageexception.py
hiraid/storagemigration.py
hiraid/storagestate.py
hiraid/v_id.py
hiraid/views.py
hiraid/historutils/__init__.py
hiraid/historutils/historutils.py
hiraid/horcm/__init__.py
hiraid/horcm/cci_exceptions.py
hiraid/horcm/cci_parser.py
hiraid/horcm/execute_cci.py
hiraid/horcm/horcm_cci.py
hiraid/horcm/horcm_instance_manager.py
hiraid/horcm/horcm_template.py
hiraid/horcm/raidqry.py
hiraid/horcm/cci_cmds/__init__.py
hiraid/horcm/cci_cmds/cci_horcmshutdown.py
hiraid/horcm/cci_cmds/cci_horcmstart.py
hiraid/horcm/cci_cmds/cci_raidqry.py
hiraid/horcm/cci_cmds/raidqry.py
hiraid-1.0.49.dist-info/LICENSE
hiraid-1.0.49.dist-info/METADATA
hiraid-1.0.49.dist-info/WHEEL
hiraid-1.0.49.dist-info/entry_points.txt
hiraid-1.0.49.dist-info/top_level.txt
hiraid-1.0.49.dist-info/RECORD
