Metadata-Version: 2.1
Name: hiraid
Version: 1.0.49
Summary: Hitachi raidcom wrapper
Home-page: https://github.com/hv-ps/hiraid
Author: Darren Chambers
Author-email: darren.chambers@hitachivantara.com
License: UNKNOWN
Platform: UNKNOWN
License-File: LICENSE
Requires-Dist: hicciexceptions
